norTools/TESTNOR.py
norTools/__init__.py
norTools/dam.py
nortools-1.2.3.dist-info/METADATA
nortools-1.2.3.dist-info/WHEEL
nortools-1.2.3.dist-info/top_level.txt
nortools-1.2.3.dist-info/RECORD
